LICENSE
README.md
setup.py
pintrest_scraper.egg-info/PKG-INFO
pintrest_scraper.egg-info/SOURCES.txt
pintrest_scraper.egg-info/dependency_links.txt
pintrest_scraper.egg-info/requires.txt
pintrest_scraper.egg-info/top_level.txt
pypi_scraper/__init__.py