Metadata-Version: 2.1
Name: pintrest-scraper
Version: 1.0.0
Summary: Web Scraping Library
Home-page: UNKNOWN
Author: DataKund
Author-email: datakund@gmail.com
License: Apache License 2.0
Platform: UNKNOWN
License-File: LICENSE
